acro/__init__.py
acro/acro.py
acro/acro_regression.py
acro/acro_stata_parser.py
acro/acro_tables.py
acro/default.yaml
acro/record.py
acro/stata_config.py
acro/utils.py
acro/version.py
acro-0.4.11.dist-info/licenses/LICENSE
acro-0.4.11.dist-info/METADATA
acro-0.4.11.dist-info/WHEEL
acro-0.4.11.dist-info/top_level.txt
acro-0.4.11.dist-info/RECORD
