Metadata-Version: 2.4
Name: acro
Version: 0.4.11
Summary: ACRO: Tools for the Semi-Automatic Checking of Research Outputs
Maintainer-email: Jim Smith <james.smith@uwe.ac.uk>
License-Expression: MIT
Project-URL: Homepage, https://github.com/AI-SDC/ACRO
Project-URL: Changelog, https://github.com/AI-SDC/ACRO/CHANGELOG.md
Project-URL: Documentation, https://ai-sdc.github.io/ACRO/
Project-URL: Bug Tracker, https://github.com/AI-SDC/ACRO/issues
Project-URL: Discussions, https://github.com/AI-SDC/ACRO/discussions
Keywords: data-privacy,data-protection,privacy,privacy-tools,statistical-disclosure-control,statistical-software
Classifier: Development Status :: 4 - Beta
Classifier: Intended Audience :: Developers
Classifier: Intended Audience :: Science/Research
Classifier: Natural Language :: English
Classifier: Programming Language :: Python :: 3.10
Classifier: Programming Language :: Python :: 3.11
Classifier: Programming Language :: Python :: 3.12
Classifier: Programming Language :: Python :: 3.13
Classifier: Programming Language :: Python :: 3.14
Classifier: Topic :: Scientific/Engineering
Classifier: Topic :: Scientific/Engineering :: Information Analysis
Classifier: Operating System :: OS Independent
Requires-Python: >=3.10
License-File: LICENSE
Requires-Dist: lxml
Requires-Dist: matplotlib
Requires-Dist: numpy
Requires-Dist: openpyxl
Requires-Dist: pandas<=2.3.3
Requires-Dist: PyYAML
Requires-Dist: statsmodels
Provides-Extra: doc
Requires-Dist: numpydoc; extra == "doc"
Requires-Dist: pytest; extra == "doc"
Requires-Dist: sphinx-autopackagesummary; extra == "doc"
Requires-Dist: sphinx-gallery; extra == "doc"
Requires-Dist: sphinx-issues; extra == "doc"
Requires-Dist: sphinx-prompt; extra == "doc"
Requires-Dist: sphinx-rtd-theme; extra == "doc"
Provides-Extra: test
Requires-Dist: pytest; extra == "test"
Requires-Dist: pytest-cov; extra == "test"
Dynamic: license-file
